get_ris_pack/__init__.py
get_ris_pack/article.py
get_ris_pack/download_pdf.py
get_ris_pack/get_info_by_id.py
get_ris_pack/get_ris.py
get_ris_pack/read_clipboard.py
get_ris-0.12.dist-info/METADATA
get_ris-0.12.dist-info/WHEEL
get_ris-0.12.dist-info/entry_points.txt
get_ris-0.12.dist-info/top_level.txt
get_ris-0.12.dist-info/zip-safe
get_ris-0.12.dist-info/RECORD
